pyrclone/__init__.py
pyrclone/rclone.exe
pyrclone/rclone_wrapper.py
pyrclonetest-0.0.7.dist-info/LICENSE
pyrclonetest-0.0.7.dist-info/METADATA
pyrclonetest-0.0.7.dist-info/WHEEL
pyrclonetest-0.0.7.dist-info/top_level.txt
pyrclonetest-0.0.7.dist-info/RECORD
