Metadata-Version: 2.1
Name: pyrclonetest
Version: 0.0.7
Summary: A package that provides a wrapper for RClone
Home-page: https://github.com/MrLYG/python-rclone.git
Author: Yuangang Li
Author-email: yuangangli@outlook.com
Classifier: Programming Language :: Python :: 3
Classifier: License :: OSI Approved :: MIT License
Classifier: Operating System :: OS Independent
Requires-Python: >=3.6
License-File: LICENSE
